{
	"items" : [
		{
			"Class" :      "6.339J",
			"label" :      "6.339J",
			"type" :       "Item",
			"Instructor" : "to be assigned"
		},
		{
			"Class" :      "6.438",
			"label" :      "6.438",
			"type" :       "Item",
			"Instructor" : "Wornell, G. W."
		},
		{
			"Class" :      "6.301",
			"label" :      "6.301",
			"type" :       "Item",
			"Instructor" : "to be assigned"
		},
		{
			"Class" :      "6.048",
			"label" :      "6.048",
			"type" :       "Item",
			"Instructor" : "Berwick, R. C."
		},
		{
			"Class" :      "6.878J",
			"label" :      "6.878J",
			"type" :       "Item",
			"Instructor" : "Kellis, M."
		},
		{
			"Class" :      "6.542J",
			"label" :      "6.542J",
			"type" :       "Item",
			"Instructor" : "Braida, L. D."
		},
		{
			"Class" :      "6.431",
			"label" :      "6.431",
			"type" :       "Item",
			"Instructor" : "Tsitsiklis, J. N."
		},
		{
			"Class" :      "6.047",
			"label" :      "6.047",
			"type" :       "Item",
			"Instructor" : "Kellis, M."
		},
		{
			"Class" :      "6.041",
			"label" :      "6.041",
			"type" :       "Item",
			"Instructor" : "Tsitsiklis, J. N."
		},
		{
			"Class" :      "6.243",
			"label" :      "6.243",
			"type" :       "Item",
			"Instructor" : "to be assigned"
		},
		{
			"Class" :      "6.45",
			"label" :      "6.45",
			"type" :       "Item",
			"Instructor" : "to be assigned"
		},
		{
			"Class" :      "6.242",
			"label" :      "6.242",
			"type" :       "Item",
			"Instructor" : "to be assigned"
		},
		{
			"Class" :      "6.101",
			"label" :      "6.101",
			"type" :       "Item",
			"Instructor" : "Roscoe, B. M."
		},
		{
			"Class" :      "6.864J",
			"label" :      "6.864J",
			"type" :       "Item",
			"Instructor" : "not offered"
		},
		{
			"Class" :      "6.859J",
			"label" :      "6.859J",
			"type" :       "Item",
			"Instructor" : "to be assigned"
		},
		{
			"Class" :      "6.838",
			"label" :      "6.838",
			"type" :       "Item",
			"Instructor" : "not offered"
		},
		{
			"Class" :      "6.837",
			"label" :      "6.837",
			"type" :       "Item",
			"Instructor" : "Durand, F. P."
		},
		{
			"Class" :      "6.021J",
			"label" :      "6.021J",
			"type" :       "Item",
			"Instructor" : "Voldman, J."
		},
		{
			"Class" :      "6.338J",
			"label" :      "6.338J",
			"type" :       "Item",
			"Instructor" : "to be assigned"
		},
		{
			"Class" :      "6.858",
			"label" :      "6.858",
			"type" :       "Item",
			"Instructor" : "Zeldovich, N. B."
		},
		{
			"Class" :      "6.946J",
			"label" :      "6.946J",
			"type" :       "Item",
			"Instructor" : "Sussman, G. J."
		},
		{
			"Class" :      "6.853",
			"label" :      "6.853",
			"type" :       "Item",
			"Instructor" : "Daskalakis, C."
		},
		{
			"Class" :      "6.877J",
			"label" :      "6.877J",
			"type" :       "Item",
			"Instructor" : "Berwick, R. C."
		},
		{
			"Class" :      "6.938",
			"label" :      "6.938",
			"type" :       "Item",
			"Instructor" : "Apostolakis, G."
		},
		{
			"Class" :      "6.111",
			"label" :      "6.111",
			"type" :       "Item",
			"Instructor" : "Stojanovic, V. M."
		},
		{
			"Class" :      "6.982J",
			"label" :      "6.982J",
			"type" :       "Item",
			"Instructor" : "Rankin, J."
		},
		{
			"Class" :      "6.524J",
			"label" :      "6.524J",
			"type" :       "Item",
			"Instructor" : "not offered"
		},
		{
			"Class" :      "6.070J",
			"label" :      "6.070J",
			"type" :       "Item",
			"Instructor" : "to be assigned"
		},
		{
			"Class" :      "6.608J",
			"label" :      "6.608J",
			"type" :       "Item",
			"Instructor" : "Barletta, W. A."
		},
		{
			"Class" :      "6.161",
			"label" :      "6.161",
			"type" :       "Item",
			"Instructor" : "Warde, C."
		},
		{
			"Class" :      "6.163",
			"label" :      "6.163",
			"type" :       "Item",
			"Instructor" : "Bales, J. W."
		},
		{
			"Class" :      "6.866",
			"label" :      "6.866",
			"type" :       "Item",
			"Instructor" : "Horn, B. K. P."
		},
		{
			"Class" :      "6.867",
			"label" :      "6.867",
			"type" :       "Item",
			"Instructor" : "to be assigned"
		},
		{
			"Class" :      "6.UAT",
			"label" :      "6.UAT",
			"type" :       "Item",
			"Instructor" : "Eng, T. L."
		},
		{
			"Class" :      "6.265J",
			"label" :      "6.265J",
			"type" :       "Item",
			"Instructor" : "to be assigned"
		},
		{
			"Class" :      "6.932",
			"label" :      "6.932",
			"type" :       "Item",
			"Instructor" : "Berners-Lee, T. J."
		},
		{
			"Class" :      "6.63",
			"label" :      "6.63",
			"type" :       "Item",
			"Instructor" : "Ippen, E. P."
		},
		{
			"Class" :      "6.152J",
			"label" :      "6.152J",
			"type" :       "Item",
			"Instructor" : "Kolodziejski, L. A."
		},
		{
			"Class" :      "6.172",
			"label" :      "6.172",
			"type" :       "Item",
			"Instructor" : "Amarasinghe, S. P."
		},
		{
			"Class" :      "6.173",
			"label" :      "6.173",
			"type" :       "Item",
			"Instructor" : "Agarwal, A."
		},
		{
			"Class" :      "6.207J",
			"label" :      "6.207J",
			"type" :       "Item",
			"Instructor" : "Dahleh, M. A."
		},
		{
			"Class" :      "6.436J",
			"label" :      "6.436J",
			"type" :       "Item",
			"Instructor" : "Tsitsiklis, J. N."
		},
		{
			"Class" :      "6.561J",
			"label" :      "6.561J",
			"type" :       "Item",
			"Instructor" : "Grodzinsky, A. J."
		},
		{
			"Class" :      "6.046J",
			"label" :      "6.046J",
			"type" :       "Item",
			"Instructor" : "Rubinfeld, R."
		},
		{
			"Class" :      "6.728",
			"label" :      "6.728",
			"type" :       "Item",
			"Instructor" : "Hagelstein, P. L."
		},
		{
			"Class" :      "6.251J",
			"label" :      "6.251J",
			"type" :       "Item",
			"Instructor" : "Schulz, A. S."
		},
		{
			"Class" :      "6.685",
			"label" :      "6.685",
			"type" :       "Item",
			"Instructor" : "Kirtley, J. L."
		},
		{
			"Class" :      "6.651J",
			"label" :      "6.651J",
			"type" :       "Item",
			"Instructor" : "Egedal-Pedersen, J."
		},
		{
			"Class" :      "6.376",
			"label" :      "6.376",
			"type" :       "Item",
			"Instructor" : "Sarpeshkar, R."
		},
		{
			"Class" :      "6.374",
			"label" :      "6.374",
			"type" :       "Item",
			"Instructor" : "Chandrakasan, A. P."
		},
		{
			"Class" :      "6.551J",
			"label" :      "6.551J",
			"type" :       "Item",
			"Instructor" : "Braida, L. D."
		},
		{
			"Class" :      "6.263J",
			"label" :      "6.263J",
			"type" :       "Item",
			"Instructor" : "to be assigned"
		},
		{
			"Class" :      "6.003",
			"label" :      "6.003",
			"type" :       "Item",
			"Instructor" : "Freeman, D. M."
		},
		{
			"Class" :      "6.002",
			"label" :      "6.002",
			"type" :       "Item",
			"Instructor" : "Perrault, D. J."
		},
		{
			"Class" :      "6.840J",
			"label" :      "6.840J",
			"type" :       "Item",
			"Instructor" : "Sipser, M. F."
		},
		{
			"Class" :      "6.341",
			"label" :      "6.341",
			"type" :       "Item",
			"Instructor" : "Oppenheim, A. V."
		},
		{
			"Class" :      "6.02",
			"label" :      "6.02",
			"type" :       "Item",
			"Instructor" : "Balakrishnan, H."
		},
		{
			"Class" :      "6.801",
			"label" :      "6.801",
			"type" :       "Item",
			"Instructor" : "Horn, B. K. P."
		},
		{
			"Class" :      "6.01",
			"label" :      "6.01",
			"type" :       "Item",
			"Instructor" : "Lozano-Perez, T."
		},
		{
			"Class" :      "6.521J",
			"label" :      "6.521J",
			"type" :       "Item",
			"Instructor" : "Voldman, J."
		},
		{
			"Class" :      "6.00",
			"label" :      "6.00",
			"type" :       "Item",
			"Instructor" : "Guttag, J. V."
		},
		{
			"Class" :      "6.005",
			"label" :      "6.005",
			"type" :       "Item",
			"Instructor" : "Miller, R. C."
		},
		{
			"Class" :      "6.004",
			"label" :      "6.004",
			"type" :       "Item",
			"Instructor" : "Ward, S. A."
		},
		{
			"Class" :      "6.007",
			"label" :      "6.007",
			"type" :       "Item",
			"Instructor" : "Bulovic, V."
		},
		{
			"Class" :      "6.006",
			"label" :      "6.006",
			"type" :       "Item",
			"Instructor" : "Devadas, S."
		},
		{
			"Class" :      "6.83",
			"label" :      "6.83",
			"type" :       "Item",
			"Instructor" : "not offered"
		},
		{
			"Class" :      "6.854J",
			"label" :      "6.854J",
			"type" :       "Item",
			"Instructor" : "Karger, D. R."
		},
		{
			"Class" :      "6.774",
			"label" :      "6.774",
			"type" :       "Item",
			"Instructor" : "Hoyt, J. L."
		},
		{
			"Class" :      "6.902J",
			"label" :      "6.902J",
			"type" :       "Item",
			"Instructor" : "Schindall, J. E."
		},
		{
			"Class" :      "6.013",
			"label" :      "6.013",
			"type" :       "Item",
			"Instructor" : "Ippen, E. P."
		},
		{
			"Class" :      "6.720J",
			"label" :      "6.720J",
			"type" :       "Item",
			"Instructor" : "del Alamo, J. A."
		},
		{
			"Class" :      "6.012",
			"label" :      "6.012",
			"type" :       "Item",
			"Instructor" : "Sodini, C. G."
		},
		{
			"Class" :      "6.814",
			"label" :      "6.814",
			"type" :       "Item",
			"Instructor" : "not offered"
		},
		{
			"Class" :      "6.434J",
			"label" :      "6.434J",
			"type" :       "Item",
			"Instructor" : "Win, M. Z."
		},
		{
			"Class" :      "6.93",
			"label" :      "6.93",
			"type" :       "Item",
			"Instructor" : "to be assigned"
		},
		{
			"Class" :      "6.805",
			"label" :      "6.805",
			"type" :       "Item",
			"Instructor" : "not offered"
		},
		{
			"Class" :      "6.763",
			"label" :      "6.763",
			"type" :       "Item",
			"Instructor" : "Orlando, T. P."
		},
		{
			"Class" :      "6.281J",
			"label" :      "6.281J",
			"type" :       "Item",
			"Instructor" : "to be assigned"
		},
		{
			"Class" :      "6.454",
			"label" :      "6.454",
			"type" :       "Item",
			"Instructor" : "to be assigned"
		},
		{
			"Class" :      "6.452",
			"label" :      "6.452",
			"type" :       "Item",
			"Instructor" : "to be assigned"
		},
		{
			"Class" :      "6.821",
			"label" :      "6.821",
			"type" :       "Item",
			"Instructor" : "not offered"
		},
		{
			"Class" :      "6.456",
			"label" :      "6.456",
			"type" :       "Item",
			"Instructor" : "Preisig, J. C."
		},
		{
			"Class" :      "6.823",
			"label" :      "6.823",
			"type" :       "Item",
			"Instructor" : "Arvind"
		},
		{
			"Class" :      "6.852J",
			"label" :      "6.852J",
			"type" :       "Item",
			"Instructor" : "Lynch, N. A."
		},
		{
			"Class" :      "6.872J",
			"label" :      "6.872J",
			"type" :       "Item",
			"Instructor" : "Szolovits, P."
		},
		{
			"Class" :      "6.337J",
			"label" :      "6.337J",
			"type" :       "Item",
			"Instructor" : "to be assigned"
		},
		{
			"Class" :      "6.331",
			"label" :      "6.331",
			"type" :       "Item",
			"Instructor" : "Roberge, J. K."
		},
		{
			"Class" :      "6.336J",
			"label" :      "6.336J",
			"type" :       "Item",
			"Instructor" : "Daniel, L."
		},
		{
			"Class" :      "6.042J",
			"label" :      "6.042J",
			"type" :       "Item",
			"Instructor" : "Meyer, A. R."
		},
		{
			"Class" :      "6.034",
			"label" :      "6.034",
			"type" :       "Item",
			"Instructor" : "Winston, P. H."
		},
		{
			"Class" :      "6.231",
			"label" :      "6.231",
			"type" :       "Item",
			"Instructor" : "to be assigned"
		},
		{
			"Class" :      "6.131",
			"label" :      "6.131",
			"type" :       "Item",
			"Instructor" : "Leeb, S. B."
		},
		{
			"Class" :      "6.631",
			"label" :      "6.631",
			"type" :       "Item",
			"Instructor" : "Fujimoto, J. G."
		},
		{
			"Class" :      "6.828",
			"label" :      "6.828",
			"type" :       "Item",
			"Instructor" : "Kaashoek, M. F."
		},
		{
			"Class" :      "6.255J",
			"label" :      "6.255J",
			"type" :       "Item",
			"Instructor" : "Parrilo, P."
		},
		{
			"Class" :      "6.142J",
			"label" :      "6.142J",
			"type" :       "Item",
			"Instructor" : "Rus, D. L."
		},
		{
			"Class" :      "6.829",
			"label" :      "6.829",
			"type" :       "Item",
			"Instructor" : "to be assigned"
		},
		{
			"Class" :      "6.637",
			"label" :      "6.637",
			"type" :       "Item",
			"Instructor" : "Warde, C."
		}
	]
}
